<manifest alg="2" build="751" opt="false" iceEnabled="true">
  <folder name="css">
    <file name="site_global.css" crc="373192293"/>
    <file name="master_fucjk.css" crc="3863019033" ref="index:index:index-copy-copy-copy:index-copy:index-copy-copy:index-copy-copy-copy-copy-copy:index-copy-copy-copy-copy"/>
    <file name="index1.css" crc="390951618" ref="index"/>
    <file name="index.css" crc="3803025486" ref="index"/>
    <file name="index-copy-copy-copy.css" crc="323537342" ref="index-copy-copy-copy"/>
    <file name="index-copy.css" crc="3808175016" ref="index-copy"/>
    <file name="index-copy-copy.css" crc="4150567625" ref="index-copy-copy"/>
    <file name="index-copy-copy-copy-copy-copy.css" crc="195509372" ref="index-copy-copy-copy-copy-copy"/>
    <file name="index-copy-copy-copy-copy.css" crc="4271051186" ref="index-copy-copy-copy-copy"/>
  </folder>
  <folder name="scripts">
    <file name="museredirect.js" crc="236897542" ref="index:index"/>
    <file name="jquery-1.8.3.min.js" crc="209076791" ref="index:index:index-copy:index-copy-copy:index-copy-copy-copy:index-copy-copy-copy-copy:index-copy-copy-copy-copy-copy:phone>index"/>
    <file name="museutils.js" crc="441941709" ref="index:index:index-copy:index-copy-copy:index-copy-copy-copy:index-copy-copy-copy-copy:index-copy-copy-copy-copy-copy:phone>index"/>
    <file name="jquery.musepolyfill.bgsize.js" crc="3956991090" ref="index:index:index-copy:index-copy-copy:index-copy-copy-copy:index-copy-copy-copy-copy:index-copy-copy-copy-copy-copy"/>
    <file name="jquery.watch.js" crc="4068933136" ref="index:index:index-copy:index-copy-copy:index-copy-copy-copy:index-copy-copy-copy-copy:index-copy-copy-copy-copy-copy:phone>index"/>
    <file name="webpro.js" crc="197321703" ref="index"/>
    <file name="musewpslideshow.js" crc="4283859919" ref="index"/>
    <file name="jquery.museoverlay.js" crc="3836522771" ref="index"/>
    <file name="touchswipe.js" crc="4156838003" ref="index"/>
  </folder>
  <folder name="images">
    <file name="tastyp-with-globe-and-topp_0007_backgroun-texture.png" crc="459079049" ref="index:index:index-copy:index-copy-copy:index-copy-copy-copy:index-copy-copy-copy-copy:index-copy-copy-copy-copy-copy"/>
    <file name="tastyp-with-globe-and-topp_0006_header.png" crc="332476209" ref="index:index:index-copy:index-copy-copy:index-copy-copy-copy:index-copy-copy-copy-copy:index-copy-copy-copy-copy-copy"/>
    <file name="tastyp-with-globe-and-topp_0000_planet-logo.png" crc="3851541027" ref="index:index:index-copy:index-copy-copy:index-copy-copy-copy:index-copy-copy-copy-copy:index-copy-copy-copy-copy-copy"/>
    <file name="tastyp-with-globe-and-topp_0001_tasty-planet---lets-eat.png" crc="221538581" ref="index:index:index-copy:index-copy-copy:index-copy-copy-copy:index-copy-copy-copy-copy:index-copy-copy-copy-copy-copy"/>
    <file name="tastyp-with-globe-and-topp_0003_cook.png" crc="165803696" ref="index:index:index-copy:index-copy-copy:index-copy-copy-copy:index-copy-copy-copy-copy:index-copy-copy-copy-copy-copy"/>
    <file name="tastyp-with-globe-and-topp_0002_eat.png" crc="233346736" ref="index:index:index-copy:index-copy-copy:index-copy-copy-copy:index-copy-copy-copy-copy:index-copy-copy-copy-copy-copy"/>
    <file name="tastyp-with-globe-and-topp_0003_cook2.png" crc="4229540519" ref="index:index:index-copy:index-copy-copy:index-copy-copy-copy:index-copy-copy-copy-copy:index-copy-copy-copy-copy-copy"/>
    <file name="tastyp-with-globe-and-topp_0003_cook3.png" crc="498455273" ref="index:index:index-copy:index-copy-copy:index-copy-copy-copy:index-copy-copy-copy-copy:index-copy-copy-copy-copy-copy"/>
    <file name="tastyp-with-globe-and-topp_0002_eat2.png" crc="4260576847" ref="index:index:index-copy:index-copy-copy:index-copy-copy-copy:index-copy-copy-copy-copy:index-copy-copy-copy-copy-copy"/>
    <file name="tastyp-with-globe-and-topp_0002_eat3.png" crc="341385100" ref="index:index:index-copy:index-copy-copy:index-copy-copy-copy:index-copy-copy-copy-copy:index-copy-copy-copy-copy-copy"/>
    <file name="tastyp-with-globe-and-topp_0002_eat4.png" crc="341385100" ref="index:index:index-copy:index-copy-copy:index-copy-copy-copy:index-copy-copy-copy-copy:index-copy-copy-copy-copy-copy"/>
    <file name="logo-u547-fr.png" crc="492522470" ref="index:index:index-copy:index-copy-copy:index-copy-copy-copy:index-copy-copy-copy-copy:index-copy-copy-copy-copy-copy"/>
    <file name="tastyp-with-globe-and-topp_0001_tasty-planet---lets-eat2.png" crc="220962928" ref="index:index:index-copy:index-copy-copy:index-copy-copy-copy:index-copy-copy-copy-copy:index-copy-copy-copy-copy-copy"/>
    <file name="tastyp-with-globe-and-topp_0005_footer.png" crc="218442489" ref="index:index:index-copy:index-copy-copy:index-copy-copy-copy:index-copy-copy-copy-copy:index-copy-copy-copy-copy-copy"/>
    <file name="smallflower.jpg" crc="3895952899" ref="index"/>
    <file name="bigflower.jpg" crc="3970824829" ref="index"/>
    <file name="leaves.jpg" crc="3844155639" ref="index"/>
  </folder>
  <folder name="phone">
    <folder name="css">
      <file name="index.css" crc="152209928" ref="phone>index"/>
    </folder>
    <file name="index.html" crc="335988644" mt="1382433475720"/>
  </folder>
  <file name="index.html" crc="3868491796" mt="1382434414417"/>
  <file name="index-copy.html" crc="176848895" mt="1382434640165"/>
  <file name="index-copy-copy.html" crc="4085353408" mt="1382434626843"/>
  <file name="index-copy-copy-copy.html" crc="21042572" mt="1382434652876"/>
  <file name="index-copy-copy-copy-copy.html" crc="457437017" mt="1382434694486"/>
  <file name="index-copy-copy-copy-copy-copy.html" crc="3871593448" mt="1382434668045"/>
</manifest>