<?xml version="1.0" encoding="ISO-8859-1"?>
<catalogue xml:lang="de">
  <message key="section_forschung">Forschung</message>
  <message key="section_studium">Studium</message>         
  <message key="section_services">Dienstleistungen &amp; Produkte</message>         
  <message key="section_info">Allgemeine Informationen</message>
  <message key="section_fakultaet">Fakult채ten &amp; Institute</message>
  <message key="section_admin">Leitung &amp; Verwaltung</message>
  <message key="section_leben">Universit채res Leben</message>

  <message key="publication_e-Learning Templates">e-Learning Templates</message>

  <message key="print_view">Druckansicht</message>
  <message key="contact">Kontakt</message>
  <message key="search">Suchen</message>
  
  <message key="university_zurich">Universit채t Z체rich</message>
  <message key="impressum">Impressum</message>
</catalogue>